clsMenu/Dataclass.py
clsMenu/MultiPage.py
clsMenu/MultiSelect.py
clsMenu/SimpleMenu.py
clsMenu/__init__.py
CL_Simple_Menu-1.2.1.dist-info/METADATA
CL_Simple_Menu-1.2.1.dist-info/WHEEL
CL_Simple_Menu-1.2.1.dist-info/top_level.txt
CL_Simple_Menu-1.2.1.dist-info/RECORD
