Metadata-Version: 2.2
Name: CL-Simple-Menu
Version: 1.2.1
Summary: A lightweight Python library for interactive command-line menus.
Home-page: https://github.com/dingzhen-vape/SimpleMenu
Author: Kono_Yalu
Author-email: 327112257@qq.com
Classifier: Programming Language :: Python :: 3
Classifier: License :: OSI Approved :: MIT License
Classifier: Operating System :: Microsoft :: Windows
Requires-Python: >=3.6
Requires-Dist: pywin32
Requires-Dist: pygetwindow
Dynamic: author
Dynamic: author-email
Dynamic: classifier
Dynamic: description
Dynamic: description-content-type
Dynamic: home-page
Dynamic: requires-dist
Dynamic: requires-python
Dynamic: summary
